gatenlp/__init__.py
gatenlp/annotation.py
gatenlp/annotation_set.py
gatenlp/annotation_utils.py
gatenlp/changelog.py
gatenlp/changelog_consts.py
gatenlp/chunking.py
gatenlp/corpora.py
gatenlp/document.py
gatenlp/features.py
gatenlp/gate_interaction.py
gatenlp/gatenlpconfig.py
gatenlp/gateworker.py
gatenlp/lib_spacy.py
gatenlp/lib_stanza.py
gatenlp/offsetmapper.py
gatenlp/span.py
gatenlp/urlfileutils.py
gatenlp/utils.py
gatenlp/version.py
gatenlp/_jars/gatetools-gatenlpworker-1.0.jar
gatenlp/corpora/__init__.py
gatenlp/corpora/base.py
gatenlp/corpora/conll.py
gatenlp/corpora/dirs.py
gatenlp/corpora/export.py
gatenlp/corpora/files.py
gatenlp/corpora/memory.py
gatenlp/gateworker/__init__.py
gatenlp/gateworker/gateworker.py
gatenlp/gateworker/gateworkerannotator.py
gatenlp/impl/__init__.py
gatenlp/impl/sortedintvls.py
gatenlp/lang/__init__.py
gatenlp/lang/de/__init__.py
gatenlp/lang/en/__init__.py
gatenlp/lang/en/gatetokenizers.py
gatenlp/pam/__init__.py
gatenlp/pam/matcher.py
gatenlp/pam/pampac.py
gatenlp/pam/pampac/__init__.py
gatenlp/pam/pampac/actions.py
gatenlp/pam/pampac/data.py
gatenlp/pam/pampac/getters.py
gatenlp/pam/pampac/pampac.py
gatenlp/pam/pampac/pampac_parsers.py
gatenlp/pam/pampac/rule.py
gatenlp/processing/__init__.py
gatenlp/processing/annotator.py
gatenlp/processing/client.py
gatenlp/processing/executor.py
gatenlp/processing/gazetteer.py
gatenlp/processing/matcher.py
gatenlp/processing/normalizer.py
gatenlp/processing/pipeline.py
gatenlp/processing/runners.py
gatenlp/processing/tokenizer.py
gatenlp/processing/client/__init__.py
gatenlp/processing/client/elg.py
gatenlp/processing/client/gatecloud.py
gatenlp/processing/client/googlenlp.py
gatenlp/processing/client/ibmnlu.py
gatenlp/processing/client/perspective.py
gatenlp/processing/client/rewire.py
gatenlp/processing/client/tagme.py
gatenlp/processing/client/textrazor.py
gatenlp/processing/emojis/__init__.py
gatenlp/processing/emojis/emojiregex.txt
gatenlp/processing/emojis/emojis.py
gatenlp-1.0.8.dist-info/LICENSE
gatenlp-1.0.8.dist-info/METADATA
gatenlp-1.0.8.dist-info/WHEEL
gatenlp-1.0.8.dist-info/entry_points.txt
gatenlp-1.0.8.dist-info/top_level.txt
gatenlp-1.0.8.dist-info/RECORD
