Metadata-Version: 2.1
Name: gatenlp
Version: 1.0.8
Summary: GATE NLP implementation in Python.
Home-page: https://github.com/GateNLP/python-gatenlp
Author: Johann Petrak
Author-email: johann.petrak@gmail.com
License: Apache License 2.0
Project-URL: Documentation, https://gatenlp.readthedocs.io
Project-URL: Source, https://github.com/GateNLP/python-gatenlp
Keywords: nlp,text processing,natural language processing
Platform: any
Classifier: Development Status :: 4 - Beta
Classifier: License :: OSI Approved :: Apache Software License
Classifier: Programming Language :: Python :: 3.7
Classifier: Programming Language :: Python :: 3.8
Classifier: Programming Language :: Python :: 3.9
Classifier: Programming Language :: Python :: 3.10
Classifier: Programming Language :: Python :: 3
Classifier: Programming Language :: Python :: 3 :: Only
Classifier: Intended Audience :: Developers
Classifier: Intended Audience :: Science/Research
Classifier: Topic :: Scientific/Engineering
Classifier: Topic :: Software Development :: Libraries
Requires-Python: >=3.7
Requires-Dist: sortedcontainers (>=2.0.0)
Requires-Dist: iobes
Provides-Extra: all
Requires-Dist: beautifulsoup4 (>=4.9.3) ; extra == 'all'
Requires-Dist: conllu ; extra == 'all'
Requires-Dist: elg ; extra == 'all'
Requires-Dist: google-api-python-client ; extra == 'all'
Requires-Dist: google-cloud-language ; extra == 'all'
Requires-Dist: ibm-watson ; extra == 'all'
Requires-Dist: iobes ; extra == 'all'
Requires-Dist: msgpack ; extra == 'all'
Requires-Dist: nltk (>=3.5) ; extra == 'all'
Requires-Dist: py4j ; extra == 'all'
Requires-Dist: pyyaml (>=5.2) ; extra == 'all'
Requires-Dist: ray[default] ; extra == 'all'
Requires-Dist: requests ; extra == 'all'
Requires-Dist: sortedcontainers (>=2.0.0) ; extra == 'all'
Requires-Dist: spacy (>=2.2) ; extra == 'all'
Requires-Dist: stanza (>=1.3.0) ; extra == 'all'
Requires-Dist: tner ; extra == 'all'
Provides-Extra: alldev
Requires-Dist: RISE ; extra == 'alldev'
Requires-Dist: bandit ; extra == 'alldev'
Requires-Dist: black[d] ; extra == 'alldev'
Requires-Dist: flake8 ; extra == 'alldev'
Requires-Dist: ipykernel ; extra == 'alldev'
Requires-Dist: ipython ; extra == 'alldev'
Requires-Dist: ipywidgets ; extra == 'alldev'
Requires-Dist: jupyterlab ; extra == 'alldev'
Requires-Dist: mypy ; extra == 'alldev'
Requires-Dist: notebook ; extra == 'alldev'
Requires-Dist: pdoc3 ; extra == 'alldev'
Requires-Dist: prospector[with_bandid,with_frosted,with_mypy,with_pyroma,with_vulture] ; extra == 'alldev'
Requires-Dist: pytest ; extra == 'alldev'
Requires-Dist: pytest-cov ; extra == 'alldev'
Requires-Dist: pytest-pep8 ; extra == 'alldev'
Requires-Dist: pytest-runner ; extra == 'alldev'
Requires-Dist: pytest-tornasync ; extra == 'alldev'
Requires-Dist: sphinx ; extra == 'alldev'
Requires-Dist: tox ; extra == 'alldev'
Requires-Dist: voila ; extra == 'alldev'
Provides-Extra: base
Requires-Dist: sortedcontainers (>=2.0.0) ; extra == 'base'
Requires-Dist: iobes ; extra == 'base'
Provides-Extra: clientelg
Requires-Dist: requests ; extra == 'clientelg'
Requires-Dist: elg ; extra == 'clientelg'
Provides-Extra: clientgatecloud
Requires-Dist: requests ; extra == 'clientgatecloud'
Provides-Extra: clientgooglenlp
Requires-Dist: google-cloud-language ; extra == 'clientgooglenlp'
Provides-Extra: clientibm
Requires-Dist: ibm-watson ; extra == 'clientibm'
Provides-Extra: clientperspective
Requires-Dist: google-api-python-client ; extra == 'clientperspective'
Provides-Extra: clients
Requires-Dist: requests ; extra == 'clients'
Requires-Dist: elg ; extra == 'clients'
Requires-Dist: ibm-watson ; extra == 'clients'
Requires-Dist: google-cloud-language ; extra == 'clients'
Requires-Dist: google-api-python-client ; extra == 'clients'
Provides-Extra: clienttagme
Requires-Dist: requests ; extra == 'clienttagme'
Provides-Extra: clienttextrazor
Requires-Dist: requests ; extra == 'clienttextrazor'
Provides-Extra: dev
Requires-Dist: pytest ; extra == 'dev'
Requires-Dist: pytest-pep8 ; extra == 'dev'
Requires-Dist: pytest-cov ; extra == 'dev'
Requires-Dist: pytest-runner ; extra == 'dev'
Requires-Dist: sphinx ; extra == 'dev'
Requires-Dist: pdoc3 ; extra == 'dev'
Requires-Dist: tox ; extra == 'dev'
Requires-Dist: mypy ; extra == 'dev'
Requires-Dist: bandit ; extra == 'dev'
Requires-Dist: prospector[with_bandid,with_frosted,with_mypy,with_pyroma,with_vulture] ; extra == 'dev'
Requires-Dist: pytest-tornasync ; extra == 'dev'
Requires-Dist: flake8 ; extra == 'dev'
Requires-Dist: black[d] ; extra == 'dev'
Provides-Extra: formats
Requires-Dist: msgpack ; extra == 'formats'
Requires-Dist: pyyaml (>=5.2) ; extra == 'formats'
Requires-Dist: beautifulsoup4 (>=4.9.3) ; extra == 'formats'
Requires-Dist: requests ; extra == 'formats'
Requires-Dist: conllu ; extra == 'formats'
Requires-Dist: iobes ; extra == 'formats'
Provides-Extra: github
Requires-Dist: flake8 ; extra == 'github'
Requires-Dist: pytest ; extra == 'github'
Requires-Dist: pytest-cov ; extra == 'github'
Requires-Dist: pytest-pep8 ; extra == 'github'
Provides-Extra: java
Requires-Dist: py4j ; extra == 'java'
Provides-Extra: mltner
Requires-Dist: tner ; extra == 'mltner'
Provides-Extra: nltk
Requires-Dist: nltk (>=3.5) ; extra == 'nltk'
Provides-Extra: notebook
Requires-Dist: ipython ; extra == 'notebook'
Requires-Dist: ipykernel ; extra == 'notebook'
Requires-Dist: jupyterlab ; extra == 'notebook'
Requires-Dist: notebook ; extra == 'notebook'
Requires-Dist: voila ; extra == 'notebook'
Requires-Dist: RISE ; extra == 'notebook'
Requires-Dist: ipywidgets ; extra == 'notebook'
Provides-Extra: ray
Requires-Dist: ray[default] ; extra == 'ray'
Provides-Extra: spacy
Requires-Dist: spacy (>=2.2) ; extra == 'spacy'
Provides-Extra: stanza
Requires-Dist: stanza (>=1.3.0) ; extra == 'stanza'
